lbdrabbit/__init__.py
lbdrabbit/_version.py
lbdrabbit/app.py
lbdrabbit/cli.py
lbdrabbit/const.py
lbdrabbit/event_model.py
lbdrabbit/stack.py
lbdrabbit/__pycache__/__init__.cpython-36.pyc
lbdrabbit/__pycache__/_version.cpython-36.pyc
lbdrabbit/__pycache__/app.cpython-36.pyc
lbdrabbit/__pycache__/cli.cpython-36.pyc
lbdrabbit/__pycache__/const.cpython-36.pyc
lbdrabbit/__pycache__/stack.cpython-36.pyc
lbdrabbit/apigw/__init__.py
lbdrabbit/apigw/http_method.py
lbdrabbit/apigw/__pycache__/__init__.cpython-36.pyc
lbdrabbit/apigw/__pycache__/http_method.cpython-36.pyc
lbdrabbit/cf/__init__.py
lbdrabbit/cf/__pycache__/__init__.cpython-36.pyc
lbdrabbit/devops/__init__.py
lbdrabbit/devops/config.py
lbdrabbit/devops/__pycache__/__init__.cpython-36.pyc
lbdrabbit/devops/__pycache__/config.cpython-36.pyc
lbdrabbit/docs/__init__.py
lbdrabbit/docs/__pycache__/__init__.cpython-36.pyc
lbdrabbit/example/__init__.py
lbdrabbit/example/app.py
lbdrabbit/example/app_config.py
lbdrabbit/example/app_config_init.py
lbdrabbit/example/cf.py
lbdrabbit/example/__pycache__/__init__.cpython-36.pyc
lbdrabbit/example/__pycache__/app.cpython-36.pyc
lbdrabbit/example/__pycache__/app_config.cpython-36.pyc
lbdrabbit/example/__pycache__/app_config_init.cpython-36.pyc
lbdrabbit/example/__pycache__/cf.cpython-36.pyc
lbdrabbit/example/handlers/__init__.py
lbdrabbit/example/handlers/auth.py
lbdrabbit/example/handlers/__pycache__/__init__.cpython-36.pyc
lbdrabbit/example/handlers/__pycache__/auth.cpython-36.pyc
lbdrabbit/example/handlers/event/__init__.py
lbdrabbit/example/handlers/event/s3.py
lbdrabbit/example/handlers/event/__pycache__/__init__.cpython-36.pyc
lbdrabbit/example/handlers/event/__pycache__/s3.cpython-36.pyc
lbdrabbit/example/handlers/rest/__init__.py
lbdrabbit/example/handlers/rest/users.py
lbdrabbit/example/handlers/rest/__pycache__/__init__.cpython-36.pyc
lbdrabbit/example/handlers/rest/__pycache__/users.cpython-36.pyc
lbdrabbit/example/handlers/rpc/__init__.py
lbdrabbit-0.0.1.dist-info/AUTHORS.rst
lbdrabbit-0.0.1.dist-info/LICENSE.txt
lbdrabbit-0.0.1.dist-info/METADATA
lbdrabbit-0.0.1.dist-info/WHEEL
lbdrabbit-0.0.1.dist-info/entry_points.txt
lbdrabbit-0.0.1.dist-info/top_level.txt
lbdrabbit-0.0.1.dist-info/RECORD
